{
  "schema_version": "1.11",
  "tool": "evoguard",
  "tool_version": "3.8.0",
  "verdict": "PASS",
  "passed": true,
  "exit_code": 0,
  "reason_code": "tests_passed",
  "reason": "the black-box pack passed (2/2) \u2014 the candidate satisfied the judge-owned protocol tests, judged from outside its own process",
  "files_changed": [
    "calculator.py"
  ],
  "protected_violations": [],
  "risk_level": "low",
  "risk_score": 0.077,
  "tests_passed": 2,
  "tests_total": 2,
  "test_command_ran": true,
  "execution_state": "completed",
  "execution_phase": "blackbox_pack",
  "verdict_source": "blackbox",
  "isolation": "docker",
  "source": "base/head",
  "base_reconstruction": null,
  "assurance": {
    "execution_state": "completed",
    "execution_phase": "blackbox_pack",
    "harness_integrity": "pre_gate_enforced",
    "report_integrity": "external_process_isolated",
    "candidate_isolation": "docker",
    "suite_isolation": "docker",
    "setup_isolation": null,
    "runtime_continuity": "not_applicable",
    "verifier_pack": {
      "configured": true,
      "present": true,
      "integrity": "verified_snapshot_pre_post",
      "identity_verified": true,
      "execution_state": "completed",
      "secrecy": "unmounted_from_candidate",
      "snapshot_sha256": "b4625484d06518d7ba2135d49c8ea5f5f2d0ce3d99889f4be4c45f2a0e9a03db"
    },
    "repo_native_suite": "not_required_blackbox_only",
    "overall_profile": "black_box_external_judge",
    "note": "The black-box phase has external_process_isolated report integrity: its judge-owned pytest does not import the candidate, so candidate report/exit forgery cannot reach that phase. The black-box phase is the only required report channel. candidate_isolation is what was OBSERVED during a launcher invocation ('docker'); preparing 'docker' alone is not evidence. A container boundary also removes the pack from the candidate's reach. See docs/BLACKBOX.md."
  },
  "diff_coverage": null,
  "baseline": null,
  "attestation": {
    "created_utc": "2026-07-19T04:24:55Z",
    "guard_version": "3.8.0",
    "mode": "blackbox",
    "candidate_sha256": "a6a78c4be2072d7cda1770a8bffe76d8be05725ccc554a530d83454522eb9425",
    "deleted_paths": [],
    "test_command": "default:python -m pytest",
    "effective_policy": {
      "mode": "blackbox",
      "isolation": "docker",
      "docker_image": "python:3.12-slim@sha256:57cd7c3a7a273101a6485ba99423ee568157882804b1124b4dd04266317710de",
      "docker_network": "none",
      "test_command": "default:python -m pytest",
      "setup_command": null,
      "trust_setup_on_host": false,
      "setup_output_globs": [],
      "protected": [],
      "allow": [],
      "allow_new_tests": false,
      "timeout": 120,
      "mem_limit_mb": 1024,
      "verifier_pack_required": true,
      "expect_verifier_pack_sha256": "b4625484d06518d7ba2135d49c8ea5f5f2d0ce3d99889f4be4c45f2a0e9a03db",
      "blackbox": true,
      "blackbox_only": true,
      "require_report_integrity": "external_process_isolated",
      "require_candidate_isolation": "docker",
      "min_diff_coverage": null,
      "baseline_evidence": false,
      "require_demonstrated_fix": false,
      "strict_harness": false,
      "policy_id": "receipt-pilot-calculator",
      "policy_version": "1"
    },
    "policy_sha256": "82b0e6c2e08c29d0105bb4305a5dc49a9958b3e363a873f095a5f2a23c180fe6",
    "junit_sha256": "2257967c09072eb979c0264bcdda4e2d53981d91d6bc3c3333ce3f9a22519319",
    "junit_digest_format": "JUNIT_XML_SHA256",
    "verifier_pack_sha256": "b4625484d06518d7ba2135d49c8ea5f5f2d0ce3d99889f4be4c45f2a0e9a03db",
    "verifier_pack_manifest": {
      "id": "receipt-pilot-calculator-cli",
      "version": "1.0.0",
      "description": "Judge-owned external protocol checks for the public calculator CLI.",
      "target_type": "cli"
    },
    "verifier_pack_tests_passed": 2,
    "verifier_pack_tests_total": 2,
    "verifier_pack_digest_format": "EVOGUARD_PACK_V2",
    "isolation_evidence": {
      "requested": "docker",
      "delivered": "docker",
      "image": "python:3.12-slim@sha256:57cd7c3a7a273101a6485ba99423ee568157882804b1124b4dd04266317710de",
      "image_digest": "sha256:25c5b8011a3425a140bf5fa73be0feabd3c0d5b323eecb19dc02437a368ae075",
      "network": "none",
      "runtime": null,
      "note": "candidate launcher prepared a network-less, read-only container; the repo copy is mounted read-only and the judge-owned pack is not mounted. A launcher receipt plus runtime-written CID is required before assurance can claim the container boundary was invoked.",
      "candidate_launcher_events": 3,
      "candidate_container_ids_observed": 3,
      "candidate_invocations": 3,
      "candidate_launcher_invocation_observed": true,
      "candidate_invocation_evidence_note": "proves the trusted pack invoked EVOGUARD_EXEC; it does not by itself prove that the pack-supplied argv exercised candidate code. Only the zero/nonzero fact is security-relevant; same-host code could discover the sidecar after its first invocation, so the raw receipt count is not an audited exact call count"
    },
    "setup_isolation_evidence": null,
    "repo_suite_isolation_evidence": null,
    "verifier_pack_isolation_evidence": null,
    "blackbox_pack_isolation_evidence": {
      "requested": "docker",
      "delivered": "docker",
      "image": "python:3.12-slim@sha256:57cd7c3a7a273101a6485ba99423ee568157882804b1124b4dd04266317710de",
      "image_digest": "sha256:25c5b8011a3425a140bf5fa73be0feabd3c0d5b323eecb19dc02437a368ae075",
      "network": "none",
      "runtime": null,
      "note": "candidate launcher prepared a network-less, read-only container; the repo copy is mounted read-only and the judge-owned pack is not mounted. A launcher receipt plus runtime-written CID is required before assurance can claim the container boundary was invoked.",
      "candidate_launcher_events": 3,
      "candidate_container_ids_observed": 3,
      "candidate_invocations": 3,
      "candidate_launcher_invocation_observed": true,
      "candidate_invocation_evidence_note": "proves the trusted pack invoked EVOGUARD_EXEC; it does not by itself prove that the pack-supplied argv exercised candidate code. Only the zero/nonzero fact is security-relevant; same-host code could discover the sidecar after its first invocation, so the raw receipt count is not an audited exact call count"
    },
    "deleted_paths_applied": [],
    "repo_suite_junit_sha256": null,
    "repo_suite_passed": null,
    "repo_suite_started": false,
    "repo_suite_completed": false,
    "repo_suite_state": "not_required_blackbox_only",
    "repo_suite_image_digest": null,
    "base_sha": "e5b3c63b949472f53697741c6fcfc1f556c0f6db",
    "head_sha": "eaec5be2d1f98ea1aa665438ec90f9531d33da2b",
    "base_tree_sha": "c06ad586eef114e05c6877e6480d19a382417edd",
    "head_tree_sha": "9ee091c8242a10a4a8051fda73f544c9b16595f1",
    "policy_id": "receipt-pilot-calculator",
    "policy_version": "1",
    "execution_state": "completed",
    "execution_phase": "blackbox_pack",
    "test_command_started": true,
    "delivered_isolation": "docker",
    "effective_candidate_isolation": "docker",
    "candidate_invocations": 3,
    "candidate_launcher_invocation_observed": true,
    "verifier_pack_present": true,
    "verifier_pack_started": true,
    "verifier_pack_completed": true,
    "setup_isolation": null,
    "runtime_tree_sha256": null,
    "runtime_tree_digest_format": null,
    "runtime_tree_entries": null,
    "runtime_tree_bytes": null,
    "runtime_identity_elapsed_ms": null,
    "runtime_continuity": null
  },
  "diagnostics": "..                                                                       [100%]\n2 passed in 1.00s\n\n"
}